modutil.py
modutil-2.0.0.dist-info/LICENSE
modutil-2.0.0.dist-info/WHEEL
modutil-2.0.0.dist-info/METADATA
modutil-2.0.0.dist-info/RECORD
