Metadata-Version: 2.1
Name: modutil
Version: 2.0.0
Summary: Help for working with modules.
Home-page: https://modutil.readthedocs.io/
License: UNKNOWN
Author: Brett Cannon
Author-email: brett@python.org
Requires-Python: >=3.7
Classifier: Development Status :: 3 - Alpha
Classifier: Intended Audience :: Developers
Classifier: License :: OSI Approved :: BSD License
Classifier: Programming Language :: Python :: 3 :: Only
Classifier: Programming Language :: Python :: 3.7
Project-URL: Development, https://github.com/brettcannon/modutil
